Workbook
Name Slicer_Shift: #N/A

Sheet shift wise report analysis
A3: Row Labels | B3: Count of Shift | C3: Sum of Cost Price | D3: Sum of Selling Price | E3: Sum of Profit %
A4: Ben | B4: 17 | C4: 20678.79 | D4: 22652.75 | E4: 1.6274615
A5: Jacob | B5: 27 | C5: 31814.22 | D5: 35185.75 | E5: 3.0147094
A6: Grand Total | B6: 44 | C6: 52493.01 | D6: 57838.5 | E6: 4.6421709

Sheet Problem
B2: Excel Data for Practice Free Download
B4: Date | C4: Sales Rep | D4: Shift | E4: Cost Price | F4: Selling Price | G4: Profit | H4: Profit % | I4: Commission | J4: Weekday
B5: 44743 | C5: Ben | D5: Night | E5: 1112.94 | F5: 1288 | G5: =F5-E5 -> 175.06 | H5: =(G5)/E5 -> 0.15729509
B6: 44743 | C6: Jacob | D6: Day | E6: 1095.5 | F6: 1250.75 | G6: =F6-E6 -> 155.25 | H6: =(G6)/E6 -> 0.14171611
B7: 44746 | C7: Ben | D7: Night | E7: 1120.94 | F7: 1295 | G7: =F7-E7 -> 174.06 | H7: =(G7)/E7 -> 0.15528039
B8: 44746 | C8: Jacob | D8: Day | E8: 1509.73 | F8: 1687.75 | G8: =F8-E8 -> 178.02 | H8: =(G8)/E8 -> 0.11791512
B9: 44747 | C9: Ben | D9: Day | E9: 1235.33 | F9: 1412.25 | G9: =F9-E9 -> 176.92 | H9: =(G9)/E9 -> 0.14321679
B10: 44747 | C10: Jacob | D10: Night | E10: 881.93 | F10: 962 | G10: =F10-E10 -> 80.07 | H10: =(G10)/E10 -> 0.090789518
B11: 44748 | C11: Ben | D11: Night | E11: 1075.7 | F11: 1142.75 | G11: =F11-E11 -> 67.05 | H11: =(G11)/E11 -> 0.062331505
B12: 44748 | C12: Jacob | D12: Day | E12: 714.58 | F12: 800.5 | G12: =F12-E12 -> 85.92 | H12: =(G12)/E12 -> 0.12023846
B13: 44749 | C13: Ben | D13: Day | E13: 1299.11 | F13: 1360 | G13: =F13-E13 -> 60.89 | H13: =(G13)/E13 -> 0.04687055
B14: 44749 | C14: Jacob | D14: Night | E14: 1087.48 | F14: 1268.5 | G14: =F14-E14 -> 181.02 | H14: =(G14)/E14 -> 0.16645823
B15: 44750 | C15: Ben | D15: Night | E15: 803.79 | F15: 907.75 | G15: =F15-E15 -> 103.96 | H15: =(G15)/E15 -> 0.12933726
B16: 44750 | C16: Jacob | D16: Day | E16: 1113.73 | F16: 1278.75 | G16: =F16-E16 -> 165.02 | H16: =(G16)/E16 -> 0.14816877
... B92: 44804 | C92: Jacob | D92: Day | E92: 951.93 | F92: 1136 | G92: =F92-E92 -> 184.07 | H92: =(G92)/E92 -> 0.19336506

Sheet Reference Data
B2: ShiftWise Daily Payment
B4: Shift | C4: Payment per Shift
B5: Day | C5: 40
B6: Night | C6: 50
B9: Commission Data
B11: Profit % | C11: Commission %
B12: Below 12% | C12: 0
B13: 12% to 20% | C13: 0.005
B14: More than 20% | C14: 0.015
B18: Week Day Calculation
B20: Digit | C20: Weekday
B21: 1 | C21: Monday
B22: 2 | C22: Tuesday
B23: 3 | C23: Wednesday
B24: 4 | C24: Thursday
B25: 5 | C25: Friday

Sheet Solution
B2: Excel Data for Practice Free Download
B4: Date | C4: Sales Rep | D4: Shift | E4: Cost Price | F4: Selling Price | G4: Profit % | H4: Commission | I4: Profit | J4: Weekday
B5: 44743 | C5: Ben | D5: Night | E5: 1112.94 | F5: 1288 | G5: =(F5-E5)/E5 -> 0.15729509 | H5: {=IFERROR(_xlfn.IFS(AND(G5>12%,G5<20%),0.5%,G5>20%,1.5%,G5<12%,"")*F5,"")} -> 6.44 | I5: =F5-E5 -> 175.06 | J5: =WEEKDAY(B5,11) -> 5
B6: 44743 | C6: Jacob | D6: Day | E6: 1095.5 | F6: 1250.75 | G6: =(F6-E6)/E6 -> 0.14171611 | H6: {=IFERROR(_xlfn.IFS(AND(G6>12%,G6<20%),0.5%,G6>20%,1.5%,G6<12%,"")*F6,"")} -> 6.25375 | I6: =F6-E6 -> 155.25 | J6: =WEEKDAY(B6,11) -> 5
B7: 44746 | C7: Ben | D7: Night | E7: 1120.94 | F7: 1295 | G7: =(F7-E7)/E7 -> 0.15528039 | H7: {=IFERROR(_xlfn.IFS(AND(G7>12%,G7<20%),0.5%,G7>20%,1.5%,G7<12%,"")*F7,"")} -> 6.475 | I7: =F7-E7 -> 174.06 | J7: =WEEKDAY(B7,11) -> 1
B8: 44746 | C8: Jacob | D8: Day | E8: 1509.73 | F8: 1687.75 | G8: =(F8-E8)/E8 -> 0.11791512 | H8: {=IFERROR(_xlfn.IFS(AND(G8>12%,G8<20%),0.5%,G8>20%,1.5%,G8<12%,"")*F8,"")} | I8: =F8-E8 -> 178.02 | J8: =WEEKDAY(B8,11) -> 1
B9: 44747 | C9: Ben | D9: Day | E9: 1235.33 | F9: 1412.25 | G9: =(F9-E9)/E9 -> 0.14321679 | H9: {=IFERROR(_xlfn.IFS(AND(G9>12%,G9<20%),0.5%,G9>20%,1.5%,G9<12%,"")*F9,"")} -> 7.06125 | I9: =F9-E9 -> 176.92 | J9: =WEEKDAY(B9,11) -> 2
B10: 44747 | C10: Jacob | D10: Night | E10: 881.93 | F10: 962 | G10: =(F10-E10)/E10 -> 0.090789518 | H10: {=IFERROR(_xlfn.IFS(AND(G10>12%,G10<20%),0.5%,G10>20%,1.5%,G10<12%,"")*F10,"")} | I10: =F10-E10 -> 80.07 | J10: =WEEKDAY(B10,11) -> 2
B11: 44748 | C11: Ben | D11: Night | E11: 1075.7 | F11: 1142.75 | G11: =(F11-E11)/E11 -> 0.062331505 | H11: {=IFERROR(_xlfn.IFS(AND(G11>12%,G11<20%),0.5%,G11>20%,1.5%,G11<12%,"")*F11,"")} | I11: =F11-E11 -> 67.05 | J11: =WEEKDAY(B11,11) -> 3
B12: 44748 | C12: Jacob | D12: Day | E12: 714.58 | F12: 800.5 | G12: =(F12-E12)/E12 -> 0.12023846 | H12: {=IFERROR(_xlfn.IFS(AND(G12>12%,G12<20%),0.5%,G12>20%,1.5%,G12<12%,"")*F12,"")} -> 4.0025 | I12: =F12-E12 -> 85.92 | J12: =WEEKDAY(B12,11) -> 3
B13: 44749 | C13: Ben | D13: Day | E13: 1299.11 | F13: 1360 | G13: =(F13-E13)/E13 -> 0.04687055 | H13: {=IFERROR(_xlfn.IFS(AND(G13>12%,G13<20%),0.5%,G13>20%,1.5%,G13<12%,"")*F13,"")} | I13: =F13-E13 -> 60.89 | J13: =WEEKDAY(B13,11) -> 4
B14: 44749 | C14: Jacob | D14: Night | E14: 1087.48 | F14: 1268.5 | G14: =(F14-E14)/E14 -> 0.16645823 | H14: {=IFERROR(_xlfn.IFS(AND(G14>12%,G14<20%),0.5%,G14>20%,1.5%,G14<12%,"")*F14,"")} -> 6.3425 | I14: =F14-E14 -> 181.02 | J14: =WEEKDAY(B14,11) -> 4
B15: 44750 | C15: Ben | D15: Night | E15: 803.79 | F15: 907.75 | G15: =(F15-E15)/E15 -> 0.12933726 | H15: {=IFERROR(_xlfn.IFS(AND(G15>12%,G15<20%),0.5%,G15>20%,1.5%,G15<12%,"")*F15,"")} -> 4.53875 | I15: =F15-E15 -> 103.96 | J15: =WEEKDAY(B15,11) -> 5
B16: 44750 | C16: Jacob | D16: Day | E16: 1113.73 | F16: 1278.75 | G16: =(F16-E16)/E16 -> 0.14816877 | H16: {=IFERROR(_xlfn.IFS(AND(G16>12%,G16<20%),0.5%,G16>20%,1.5%,G16<12%,"")*F16,"")} -> 6.39375 | I16: =F16-E16 -> 165.02 | J16: =WEEKDAY(B16,11) -> 5
... B19: 44754 | C19: Ben | D19: Night | E19: 1382.27 | F19: 1550.25 | G19: =(F19-E19)/E19 -> 0.12152474 | H19: {=IFERROR(_xlfn.IFS(AND(G19>12%,G19<20%),0.5%,G19>20%,1.5%,G19<12%,"")*F19,"")} -> 7.75125 | I19: =F19-E19 -> 167.98 | J19: =WEEKDAY(B19,11) -> 2
B20: 44754 | C20: Jacob | D20: Day | E20: 1515.76 | F20: 1622.75 | G20: =(F20-E20)/E20 -> 0.070585053 | H20: {=IFERROR(_xlfn.IFS(AND(G20>12%,G20<20%),0.5%,G20>20%,1.5%,G20<12%,"")*F20,"")} | I20: =F20-E20 -> 106.99 | J20: =WEEKDAY(B20,11) -> 2 | L20: Task 03
B21: 44755 | C21: Ben | D21: Day | E21: 1264.56 | F21: 1328.5 | G21: =(F21-E21)/E21 -> 0.050563042 | H21: {=IFERROR(_xlfn.IFS(AND(G21>12%,G21<20%),0.5%,G21>20%,1.5%,G21<12%,"")*F21,"")} | I21: =F21-E21 -> 63.94 | J21: =WEEKDAY(B21,11) -> 3 | M21: Name | N21: Shift
B22: 44755 | C22: Jacob | D22: Night | E22: 1251.98 | F22: 1402 | G22: =(F22-E22)/E22 -> 0.1198262 | H22: {=IFERROR(_xlfn.IFS(AND(G22>12%,G22<20%),0.5%,G22>20%,1.5%,G22<12%,"")*F22,"")} | I22: =F22-E22 -> 150.02 | J22: =WEEKDAY(B22,11) -> 3 | N22: Day | O22: Night
B23: 44756 | C23: Ben | D23: Night | E23: 986.11 | F23: 1054 | G23: =(F23-E23)/E23 -> 0.068846275 | H23: {=IFERROR(_xlfn.IFS(AND(G23>12%,G23<20%),0.5%,G23>20%,1.5%,G23<12%,"")*F23,"")} | I23: =F23-E23 -> 67.89 | J23: =WEEKDAY(B23,11) -> 4 | M23: Ben | N23: =COUNTIFS($C$5:$C$92,M23,$D$5:$D$92,N$22) -> 17 | O23: =COUNTIFS($C$5:$C$92,M23,$D$5:$D$92,O$22) -> 27
B24: 44756 | C24: Jacob | D24: Day | E24: 1514.2 | F24: 1571.25 | G24: =(F24-E24)/E24 -> 0.037676661 | H24: {=IFERROR(_xlfn.IFS(AND(G24>12%,G24<20%),0.5%,G24>20%,1.5%,G24<12%,"")*F24,"")} | I24: =F24-E24 -> 57.05 | J24: =WEEKDAY(B24,11) -> 4 | M24: Jacob | N24: =COUNTIFS($C$5:$C$92,M24,$D$5:$D$92,N$22) -> 27 | O24: =COUNTIFS($C$5:$C$92,M24,$D$5:$D$92,O$22) -> 17
B25: 44757 | C25: Ben | D25: Day | E25: 1318.85 | F25: 1454.75 | G25: =(F25-E25)/E25 -> 0.10304432 | H25: {=IFERROR(_xlfn.IFS(AND(G25>12%,G25<20%),0.5%,G25>20%,1.5%,G25<12%,"")*F25,"")} | I25: =F25-E25 -> 135.9 | J25: =WEEKDAY(B25,11) -> 5
B26: 44757 | C26: Jacob | D26: Night | E26: 1495.11 | F26: 1655 | G26: =(F26-E26)/E26 -> 0.10694196 | H26: {=IFERROR(_xlfn.IFS(AND(G26>12%,G26<20%),0.5%,G26>20%,1.5%,G26<12%,"")*F26,"")} | I26: =F26-E26 -> 159.89 | J26: =WEEKDAY(B26,11) -> 5 | L26: Task 04
B27: 44760 | C27: Ben | D27: Night | E27: 1187.7 | F27: 1297.75 | G27: =(F27-E27)/E27 -> 0.092658079 | H27: {=IFERROR(_xlfn.IFS(AND(G27>12%,G27<20%),0.5%,G27>20%,1.5%,G27<12%,"")*F27,"")} | I27: =F27-E27 -> 110.05 | J27: =WEEKDAY(B27,11) -> 1 | M27: Name | N27: Shift | P27: Total
B28: 44760 | C28: Jacob | D28: Day | E28: 1150.74 | F28: 1225.75 | G28: =(F28-E28)/E28 -> 0.065184142 | H28: {=IFERROR(_xlfn.IFS(AND(G28>12%,G28<20%),0.5%,G28>20%,1.5%,G28<12%,"")*F28,"")} | I28: =F28-E28 -> 75.01 | J28: =WEEKDAY(B28,11) -> 1 | N28: Day | O28: Night
B29: 44761 | C29: Ben | D29: Day | E29: 1562.68 | F29: 1736.75 | G29: =(F29-E29)/E29 -> 0.11139197 | H29: {=IFERROR(_xlfn.IFS(AND(G29>12%,G29<20%),0.5%,G29>20%,1.5%,G29<12%,"")*F29,"")} | I29: =F29-E29 -> 174.07 | J29: =WEEKDAY(B29,11) -> 2 | M29: Ben | N29: =N23*'Reference Data'!$C$5 -> 680 | O29: =O23*'Reference Data'!$C$6 -> 1350 | P29: =SUM(N29:O29) -> 2030
B30: 44761 | C30: Jacob | D30: Night | E30: 1514.13 | F30: 1620.25 | G30: =(F30-E30)/E30 -> 0.070086452 | H30: {=IFERROR(_xlfn.IFS(AND(G30>12%,G30<20%),0.5%,G30>20%,1.5%,G30<12%,"")*F30,"")} | I30: =F30-E30 -> 106.12 | J30: =WEEKDAY(B30,11) -> 2 | M30: Jacob | N30: =N24*'Reference Data'!$C$5 -> 1080 | O30: =O24*'Reference Data'!$C$6 -> 850 | P30: =SUM(N30:O30) -> 1930
B31: 44762 | C31: Ben | D31: Night | E31: 778.27 | F31: 930.25 | G31: =(F31-E31)/E31 -> 0.19527927 | H31: {=IFERROR(_xlfn.IFS(AND(G31>12%,G31<20%),0.5%,G31>20%,1.5%,G31<12%,"")*F31,"")} -> 4.65125 | I31: =F31-E31 -> 151.98 | J31: =WEEKDAY(B31,11) -> 3
B32: 44762 | C32: Jacob | D32: Day | E32: 1270.66 | F32: 1334.75 | G32: =(F32-E32)/E32 -> 0.050438355 | H32: {=IFERROR(_xlfn.IFS(AND(G32>12%,G32<20%),0.5%,G32>20%,1.5%,G32<12%,"")*F32,"")} | I32: =F32-E32 -> 64.09 | J32: =WEEKDAY(B32,11) -> 3 | L32: Task 05
B33: 44763 | C33: Ben | D33: Day | E33: 766.72 | F33: 841.75 | G33: =(F33-E33)/E33 -> 0.09785841 | H33: {=IFERROR(_xlfn.IFS(AND(G33>12%,G33<20%),0.5%,G33>20%,1.5%,G33<12%,"")*F33,"")} | I33: =F33-E33 -> 75.03 | J33: =WEEKDAY(B33,11) -> 4 | M33: Day | N33: Total | O33: Total Profit | P33: Mean Profit
B34: 44763 | C34: Jacob | D34: Night | E34: 1041.13 | F34: 1157.25 | G34: =(F34-E34)/E34 -> 0.11153266 | H34: {=IFERROR(_xlfn.IFS(AND(G34>12%,G34<20%),0.5%,G34>20%,1.5%,G34<12%,"")*F34,"")} | I34: =F34-E34 -> 116.12 | J34: =WEEKDAY(B34,11) -> 4 | M34: Monday | N34: =COUNTIF($J$5:$J$92,'Reference Data'!B21) -> 18 | O34: =SUMIF($J$5:$J$92,'Reference Data'!B21,$I$5:$I$92) -> 2329.54 | P34: =O34/N34 -> 129.41889
B35: 44764 | C35: Ben | D35: Night | E35: 1218.08 | F35: 1344 | G35: =(F35-E35)/E35 -> 0.1033758 | H35: {=IFERROR(_xlfn.IFS(AND(G35>12%,G35<20%),0.5%,G35>20%,1.5%,G35<12%,"")*F35,"")} | I35: =F35-E35 -> 125.92 | J35: =WEEKDAY(B35,11) -> 5 | M35: Tuesday | N35: =COUNTIF($J$5:$J$92,'Reference Data'!B22) -> 18 | O35: =SUMIF($J$5:$J$92,'Reference Data'!B22,$I$5:$I$92) -> 2530 | P35: =O35/N35 -> 140.55556
B36: 44764 | C36: Jacob | D36: Day | E36: 1016.36 | F36: 1108.25 | G36: =(F36-E36)/E36 -> 0.090410878 | H36: {=IFERROR(_xlfn.IFS(AND(G36>12%,G36<20%),0.5%,G36>20%,1.5%,G36<12%,"")*F36,"")} | I36: =F36-E36 -> 91.89 | J36: =WEEKDAY(B36,11) -> 5 | M36: Wednesday | N36: =COUNTIF($J$5:$J$92,'Reference Data'!B23) -> 18 | O36: =SUMIF($J$5:$J$92,'Reference Data'!B23,$I$5:$I$92) -> 2035.7 | P36: =O36/N36 -> 113.09444
B37: 44767 | C37: Ben | D37: Day | E37: 1576.91 | F37: 1683 | G37: =(F37-E37)/E37 -> 0.067277143 | H37: {=IFERROR(_xlfn.IFS(AND(G37>12%,G37<20%),0.5%,G37>20%,1.5%,G37<12%,"")*F37,"")} | I37: =F37-E37 -> 106.09 | J37: =WEEKDAY(B37,11) -> 1 | M37: Thursday | N37: =COUNTIF($J$5:$J$92,'Reference Data'!B24) -> 16 | O37: =SUMIF($J$5:$J$92,'Reference Data'!B24,$I$5:$I$92) -> 1808.98 | P37: =O37/N37 -> 113.06125
B38: 44767 | C38: Jacob | D38: Night | E38: 870.02 | F38: 997 | G38: =(F38-E38)/E38 -> 0.14595067 | H38: {=IFERROR(_xlfn.IFS(AND(G38>12%,G38<20%),0.5%,G38>20%,1.5%,G38<12%,"")*F38,"")} -> 4.985 | I38: =F38-E38 -> 126.98 | J38: =WEEKDAY(B38,11) -> 1 | M38: Friday | N38: =COUNTIF($J$5:$J$92,'Reference Data'!B25) -> 18 | O38: =SUMIF($J$5:$J$92,'Reference Data'!B25,$I$5:$I$92) -> 2281.09 | P38: =O38/N38 -> 126.72722
B39: 44768 | C39: Ben | D39: Night | E39: 1145.26 | F39: 1344.25 | G39: =(F39-E39)/E39 -> 0.17375094 | H39: {=IFERROR(_xlfn.IFS(AND(G39>12%,G39<20%),0.5%,G39>20%,1.5%,G39<12%,"")*F39,"")} -> 6.72125 | I39: =F39-E39 -> 198.99 | J39: =WEEKDAY(B39,11) -> 2
B40: 44768 | C40: Jacob | D40: Day | E40: 1313.05 | F40: 1504 | G40: =(F40-E40)/E40 -> 0.14542477 | H40: {=IFERROR(_xlfn.IFS(AND(G40>12%,G40<20%),0.5%,G40>20%,1.5%,G40<12%,"")*F40,"")} -> 7.52 | I40: =F40-E40 -> 190.95 | J40: =WEEKDAY(B40,11) -> 2 | M40: The company earns maximum average profit on Tuesday.
B41: 44769 | C41: Ben | D41: Day | E41: 833.49 | F41: 906.5 | G41: =(F41-E41)/E41 -> 0.087595532 | H41: {=IFERROR(_xlfn.IFS(AND(G41>12%,G41<20%),0.5%,G41>20%,1.5%,G41<12%,"")*F41,"")} | I41: =F41-E41 -> 73.01 | J41: =WEEKDAY(B41,11) -> 3
B42: 44769 | C42: Jacob | D42: Night | E42: 1578.85 | F42: 1711.75 | G42: =(F42-E42)/E42 -> 0.084175191 | H42: {=IFERROR(_xlfn.IFS(AND(G42>12%,G42<20%),0.5%,G42>20%,1.5%,G42<12%,"")*F42,"")} | I42: =F42-E42 -> 132.9 | J42: =WEEKDAY(B42,11) -> 3 | L42: Task 05 Alternate Solution (Without Helper Columns, Using SUMPRODUCT)
B43: 44770 | C43: Ben | D43: Night | E43: 1314.78 | F43: 1371.75 | G43: =(F43-E43)/E43 -> 0.043330443 | H43: {=IFERROR(_xlfn.IFS(AND(G43>12%,G43<20%),0.5%,G43>20%,1.5%,G43<12%,"")*F43,"")} | I43: =F43-E43 -> 56.97 | J43: =WEEKDAY(B43,11) -> 4
B44: 44770 | C44: Jacob | D44: Day | E44: 972.81 | F44: 1139.75 | G44: =(F44-E44)/E44 -> 0.17160597 | H44: {=IFERROR(_xlfn.IFS(AND(G44>12%,G44<20%),0.5%,G44>20%,1.5%,G44<12%,"")*F44,"")} -> 5.69875 | I44: =F44-E44 -> 166.94 | J44: =WEEKDAY(B44,11) -> 4 | M44: Day | N44: Total | O44: Total Profit | P44: Mean Profit
B45: 44771 | C45: Ben | D45: Day | E45: 1551.16 | F45: 1721.25 | G45: =(F45-E45)/E45 -> 0.10965342 | H45: {=IFERROR(_xlfn.IFS(AND(G45>12%,G45<20%),0.5%,G45>20%,1.5%,G45<12%,"")*F45,"")} | I45: =F45-E45 -> 170.09 | J45: =WEEKDAY(B45,11) -> 5 | M45: Monday | N45: {=SUMPRODUCT(--(WEEKDAY($B$5:$B$92,11)='Reference Data'!B21))} -> 18 | O45: {=SUMPRODUCT((WEEKDAY($B$5:$B$92,11)='Reference Data'!B21)*($F$5:$F$92-$E$5:$E$92))} -> 2329.54 | P45: =O45/N45 -> 129.41889
B46: 44771 | C46: Jacob | D46: Night | E46: 1366.59 | F46: 1418.5 | G46: =(F46-E46)/E46 -> 0.037985058 | H46: {=IFERROR(_xlfn.IFS(AND(G46>12%,G46<20%),0.5%,G46>20%,1.5%,G46<12%,"")*F46,"")} | I46: =F46-E46 -> 51.91 | J46: =WEEKDAY(B46,11) -> 5 | M46: Tuesday | N46: {=SUMPRODUCT(--(WEEKDAY($B$5:$B$92,11)='Reference Data'!B22))} -> 18 | O46: {=SUMPRODUCT((WEEKDAY($B$5:$B$92,11)='Reference Data'!B22)*($F$5:$F$92-$E$5:$E$92))} -> 2530 | P46: =O46/N46 -> 140.55556
B47: 44774 | C47: Ben | D47: Night | E47: 1466.66 | F47: 1624.75 | G47: =(F47-E47)/E47 -> 0.10778913 | H47: {=IFERROR(_xlfn.IFS(AND(G47>12%,G47<20%),0.5%,G47>20%,1.5%,G47<12%,"")*F47,"")} | I47: =F47-E47 -> 158.09 | J47: =WEEKDAY(B47,11) -> 1 | M47: Wednesday | N47: {=SUMPRODUCT(--(WEEKDAY($B$5:$B$92,11)='Reference Data'!B23))} -> 18 | O47: {=SUMPRODUCT((WEEKDAY($B$5:$B$92,11)='Reference Data'!B23)*($F$5:$F$92-$E$5:$E$92))} -> 2035.7 | P47: =O47/N47 -> 113.09444
B48: 44774 | C48: Jacob | D48: Day | E48: 1594.15 | F48: 1682.25 | G48: =(F48-E48)/E48 -> 0.055264561 | H48: {=IFERROR(_xlfn.IFS(AND(G48>12%,G48<20%),0.5%,G48>20%,1.5%,G48<12%,"")*F48,"")} | I48: =F48-E48 -> 88.1 | J48: =WEEKDAY(B48,11) -> 1 | M48: Thursday | N48: {=SUMPRODUCT(--(WEEKDAY($B$5:$B$92,11)='Reference Data'!B24))} -> 16 | O48: {=SUMPRODUCT((WEEKDAY($B$5:$B$92,11)='Reference Data'!B24)*($F$5:$F$92-$E$5:$E$92))} -> 1808.98 | P48: =O48/N48 -> 113.06125
B49: 44775 | C49: Ben | D49: Night | E49: 1580.98 | F49: 1679 | G49: =(F49-E49)/E49 -> 0.061999519 | H49: {=IFERROR(_xlfn.IFS(AND(G49>12%,G49<20%),0.5%,G49>20%,1.5%,G49<12%,"")*F49,"")} | I49: =F49-E49 -> 98.02 | J49: =WEEKDAY(B49,11) -> 2 | M49: Friday | N49: {=SUMPRODUCT(--(WEEKDAY($B$5:$B$92,11)='Reference Data'!B25))} -> 18 | O49: {=SUMPRODUCT((WEEKDAY($B$5:$B$92,11)='Reference Data'!B25)*($F$5:$F$92-$E$5:$E$92))} -> 2281.09 | P49: =O49/N49 -> 126.72722
B50: 44775 | C50: Jacob | D50: Day | E50: 916.97 | F50: 1025 | G50: =(F50-E50)/E50 -> 0.11781192 | H50: {=IFERROR(_xlfn.IFS(AND(G50>12%,G50<20%),0.5%,G50>20%,1.5%,G50<12%,"")*F50,"")} | I50: =F50-E50 -> 108.03 | J50: =WEEKDAY(B50,11) -> 2
B51: 44776 | C51: Ben | D51: Night | E51: 726.12 | F51: 838 | G51: =(F51-E51)/E51 -> 0.15407922 | H51: {=IFERROR(_xlfn.IFS(AND(G51>12%,G51<20%),0.5%,G51>20%,1.5%,G51<12%,"")*F51,"")} -> 4.19 | I51: =F51-E51 -> 111.88 | J51: =WEEKDAY(B51,11) -> 3
B52: 44776 | C52: Jacob | D52: Day | E52: 1461.44 | F52: 1599.5 | G52: =(F52-E52)/E52 -> 0.094468469 | H52: {=IFERROR(_xlfn.IFS(AND(G52>12%,G52<20%),0.5%,G52>20%,1.5%,G52<12%,"")*F52,"")} | I52: =F52-E52 -> 138.06 | J52: =WEEKDAY(B52,11) -> 3
B53: 44777 | C53: Ben | D53: Day | E53: 1176.26 | F53: 1263.25 | G53: =(F53-E53)/E53 -> 0.073954738 | H53: {=IFERROR(_xlfn.IFS(AND(G53>12%,G53<20%),0.5%,G53>20%,1.5%,G53<12%,"")*F53,"")} | I53: =F53-E53 -> 86.99 | J53: =WEEKDAY(B53,11) -> 4
B54: 44777 | C54: Jacob | D54: Night | E54: 825.12 | F54: 1004 | G54: =(F54-E54)/E54 -> 0.21679271 | H54: {=IFERROR(_xlfn.IFS(AND(G54>12%,G54<20%),0.5%,G54>20%,1.5%,G54<12%,"")*F54,"")} -> 15.06 | I54: =F54-E54 -> 178.88 | J54: =WEEKDAY(B54,11) -> 4
B55: 44778 | C55: Ben | D55: Night | E55: 1034.97 | F55: 1091 | G55: =(F55-E55)/E55 -> 0.054136835 | H55: {=IFERROR(_xlfn.IFS(AND(G55>12%,G55<20%),0.5%,G55>20%,1.5%,G55<12%,"")*F55,"")} | I55: =F55-E55 -> 56.03 | J55: =WEEKDAY(B55,11) -> 5
B56: 44778 | C56: Jacob | D56: Day | E56: 939.94 | F56: 1045 | G56: =(F56-E56)/E56 -> 0.11177309 | H56: {=IFERROR(_xlfn.IFS(AND(G56>12%,G56<20%),0.5%,G56>20%,1.5%,G56<12%,"")*F56,"")} | I56: =F56-E56 -> 105.06 | J56: =WEEKDAY(B56,11) -> 5
B57: 44781 | C57: Ben | D57: Day | E57: 1429.63 | F57: 1570.75 | G57: =(F57-E57)/E57 -> 0.098710855 | H57: {=IFERROR(_xlfn.IFS(AND(G57>12%,G57<20%),0.5%,G57>20%,1.5%,G57<12%,"")*F57,"")} | I57: =F57-E57 -> 141.12 | J57: =WEEKDAY(B57,11) -> 1
B58: 44781 | C58: Jacob | D58: Night | E58: 1009.06 | F58: 1189 | G58: =(F58-E58)/E58 -> 0.17832438 | H58: {=IFERROR(_xlfn.IFS(AND(G58>12%,G58<20%),0.5%,G58>20%,1.5%,G58<12%,"")*F58,"")} -> 5.945 | I58: =F58-E58 -> 179.94 | J58: =WEEKDAY(B58,11) -> 1
B59: 44782 | C59: Ben | D59: Night | E59: 974.45 | F59: 1152.5 | G59: =(F59-E59)/E59 -> 0.18271846 | H59: {=IFERROR(_xlfn.IFS(AND(G59>12%,G59<20%),0.5%,G59>20%,1.5%,G59<12%,"")*F59,"")} -> 5.7625 | I59: =F59-E59 -> 178.05 | J59: =WEEKDAY(B59,11) -> 2
B60: 44782 | C60: Jacob | D60: Day | E60: 1511.87 | F60: 1688.75 | G60: =(F60-E60)/E60 -> 0.11699419 | H60: {=IFERROR(_xlfn.IFS(AND(G60>12%,G60<20%),0.5%,G60>20%,1.5%,G60<12%,"")*F60,"")} | I60: =F60-E60 -> 176.88 | J60: =WEEKDAY(B60,11) -> 2
B61: 44783 | C61: Ben | D61: Night | E61: 1103.76 | F61: 1256.75 | G61: =(F61-E61)/E61 -> 0.13860803 | H61: {=IFERROR(_xlfn.IFS(AND(G61>12%,G61<20%),0.5%,G61>20%,1.5%,G61<12%,"")*F61,"")} -> 6.28375 | I61: =F61-E61 -> 152.99 | J61: =WEEKDAY(B61,11) -> 3
... B92: 44804 | C92: Jacob | D92: Day | E92: 951.93 | F92: 1136 | G92: =(F92-E92)/E92 -> 0.19336506 | H92: {=IFERROR(_xlfn.IFS(AND(G92>12%,G92<20%),0.5%,G92>20%,1.5%,G92<12%,"")*F92,"")} -> 5.68 | I92: =F92-E92 -> 184.07 | J92: =WEEKDAY(B92,11) -> 3
